google_bucket_fetcher/__init__.py
google_bucket_fetcher/google_bucket_fetcher.py
google_bucket_fetcher-0.1.3.dist-info/AUTHORS.rst
google_bucket_fetcher-0.1.3.dist-info/LICENSE
google_bucket_fetcher-0.1.3.dist-info/METADATA
google_bucket_fetcher-0.1.3.dist-info/WHEEL
google_bucket_fetcher-0.1.3.dist-info/top_level.txt
google_bucket_fetcher-0.1.3.dist-info/RECORD
