Metadata-Version: 2.1
Name: google-bucket-fetcher
Version: 0.1.3
Summary: A Python package to access bucjet data from Google Cloud Storage
Home-page: https://github.com/eduardo-menezes/google_bucket_fetcher
Author: Eduardo Oliveira Menezes
Author-email: eduardomenezes.dev@gmail.com
License: MIT license
Keywords: google_bucket_fetcher
Classifier: Development Status :: 2 - Pre-Alpha
Classifier: Intended Audience :: Developers
Classifier: License :: OSI Approved :: MIT License
Classifier: Natural Language :: English
Classifier: Programming Language :: Python :: 3
Classifier: Programming Language :: Python :: 3.6
Classifier: Programming Language :: Python :: 3.7
Classifier: Programming Language :: Python :: 3.8
Requires-Python: >=3.6
License-File: LICENSE
License-File: AUTHORS.rst
